CHANGELOG.txt
LICENCE.txt
MANIFEST.in
README.txt
mattia.jpg
setup.py
simone.jpg
smonkeylibrary/__init__.py
smonkeylibrary.egg-info/PKG-INFO
smonkeylibrary.egg-info/SOURCES.txt
smonkeylibrary.egg-info/dependency_links.txt
smonkeylibrary.egg-info/top_level.txt