Metadata-Version: 1.1
Name: smonkeylibrary
Version: 0.0.5
Summary: The smonkey library
Home-page: UNKNOWN
Author: Mattia Rigiroli
Author-email: mattiarigiroli@gmail.com
License: MIT
Keywords: calculator
Platform: UNKNOWN
Classifier: Development Status :: 5 - Production/Stable
Classifier: Intended Audience :: Education
Classifier: Operating System :: Microsoft :: Windows :: Windows 10
Classifier: License :: OSI Approved :: MIT License
Classifier: Programming Language :: Python :: 3
